[
  {
    "station": "agt",
    "name": "Agartala",
    "state": "Tripura",
    "caz": "2025-10-17 17:02:24",
    "ppi": "2025-10-17 17:02:24",
    "sri": "2025-10-17 17:02:24",
    "ppz": "2025-10-17 17:00:28",
    "ppv": "2025-10-17 17:02:24",
    "vp2": "2025-10-17 17:02:24",
    "pac": "2025-10-17 08:30:00",
    "overall": "\u2714\ufe0f"
  },
  {
    "station": "aya",
    "name": "Delhi Ayanagar",
    "state": "Delhi",
    "caz": "2025-10-17 17:00:05",
    "ppi": "2025-10-17 17:10:01",
    "sri": "2025-10-17 17:00:05",
    "ppz": "2025-10-17 17:06:59",
    "ppv": "2025-10-17 17:10:01",
    "vp2": "2025-10-17 17:00:05",
    "pac": "2025-10-17 08:30:01",
    "overall": "\u2714\ufe0f"
  },
  {
    "station": "bnh",
    "name": "Banihal",
    "state": "Jammu & Kashmir",
    "caz": "2025-10-14 10:10:01",
    "ppi": "2025-10-14 10:30:01",
    "sri": "2025-10-14 10:30:01",
    "ppz": "2025-10-14 10:26:55",
    "ppv": "2025-10-14 10:30:01",
    "vp2": "2025-10-14 10:20:01",
    "pac": "2025-10-11 08:30:02",
    "overall": "\u274c"
  },
  {
    "station": "bhj",
    "name": "Bhuj",
    "state": "Gujrat",
    "caz": "2025-10-17 16:50:45",
    "ppi": "2025-10-17 16:50:45",
    "sri": "2025-10-17 16:50:45",
    "ppz": "2025-10-17 16:49:21",
    "ppv": "2025-10-17 16:50:45",
    "vp2": "2025-10-17 16:20:32",
    "pac": "2025-10-17 14:48:30",
    "overall": "\u2714\ufe0f"
  },
  {
    "station": "bhp",
    "name": "Bhopal",
    "state": "Madhya Pradesh",
    "caz": "2025-10-17 17:12:22",
    "ppi": "2025-10-17 17:12:22",
    "sri": "2025-10-17 17:12:22",
    "ppz": "2025-10-17 17:20:27",
    "ppv": "2025-10-17 17:12:22",
    "vp2": "2025-10-17 17:12:22",
    "pac": "2025-10-17 08:30:00",
    "overall": "\u2714\ufe0f"
  },
  {
    "station": "cpj",
    "name": "Cherapunji",
    "state": "Meghalaya",
    "caz": "2025-08-17 09:32:48",
    "ppi": "2025-08-17 09:32:48",
    "sri": "2025-08-17 09:32:48",
    "ppz": "2025-08-17 09:31:03",
    "ppv": "2025-08-17 09:32:48",
    "vp2": "2025-08-17 09:32:48",
    "pac": "2025-05-23 21:55:27",
    "overall": "\u274c"
  },
  {
    "station": "cni",
    "name": "Chennai",
    "state": "Tamilnadu",
    "caz": "2025-10-17 17:00:00",
    "ppi": "2025-10-17 17:20:04",
    "sri": "2025-10-17 17:00:00",
    "ppz": "2025-10-17 17:06:00",
    "ppv": "2025-10-17 17:00:00",
    "vp2": "1120-07-17 05:30:00",
    "pac": "2025-10-17 08:30:00",
    "overall": "\u2714\ufe0f"
  },
  {
    "station": "dli",
    "name": "Delhi Hq",
    "state": "Delhi",
    "manual_status": "TX Fault Since 16.06.2025",
    "overall": "\u274c"
  },
  {
    "station": "dlh",
    "name": "Delhi Palam",
    "state": "Delhi",
    "caz": "2025-10-17 17:12:28",
    "ppi": "2025-10-17 17:13:01",
    "sri": "2025-10-17 17:12:28",
    "ppz": "2025-10-17 17:10:27",
    "ppv": "2025-10-17 17:12:28",
    "vp2": "2025-10-17 17:12:28",
    "pac": "2025-10-17 08:30:00",
    "overall": "\u2714\ufe0f"
  },
  {
    "station": "goa",
    "name": "Goa",
    "state": "Goa",
    "caz": "2025-10-17 17:12:35",
    "ppi": "2025-10-17 17:17:00",
    "sri": "2025-10-17 17:12:35",
    "ppz": "2025-10-17 17:10:31",
    "ppv": "2025-10-17 17:07:34",
    "vp2": "2025-10-17 17:12:35",
    "pac": "2025-10-17 08:30:00",
    "overall": "\u2714\ufe0f"
  },
  {
    "station": "gop",
    "name": "Gopalpur",
    "state": "Odhisa",
    "manual_status": "Under Upgradation Since 2024-12-14",
    "overall": "\u274c"
  },
  {
    "station": "hyd",
    "name": "Hyderabad",
    "state": "Telangana",
    "caz": "2025-10-17 17:02:23",
    "ppi": "2025-10-17 17:02:23",
    "sri": "2025-10-17 17:02:23",
    "ppz": "2025-10-17 17:20:21",
    "ppv": "2025-10-17 17:02:23",
    "vp2": "2025-10-17 17:02:23",
    "pac": "2025-10-17 08:30:00",
    "overall": "\u2714\ufe0f"
  },
  {
    "station": "jot",
    "name": "Jot",
    "state": "Himachal Pradesh",
    "caz": "2025-10-17 16:20:01",
    "ppi": "2025-10-17 16:20:01",
    "sri": "2025-10-17 16:40:01",
    "ppz": "2025-10-17 14:36:55",
    "ppv": "2025-10-17 16:40:01",
    "vp2": "2025-10-17 16:40:01",
    "pac": "2025-10-17 08:30:01",
    "overall": "\u2714\ufe0f"
  },
  {
    "station": "jmu",
    "name": "Jammu",
    "state": "Jammu & Kashmir",
    "manual_status": "Transformer Blast Followed By Sudden Blast Since 2025-09-02",
    "overall": "\u274c"
  },
  {
    "station": "jpr",
    "name": "Jaipur",
    "state": "Rajasthan",
    "caz": "2025-10-17 17:02:54",
    "ppi": "2025-10-17 17:02:54",
    "sri": "Invalid",
    "ppz": "2025-10-17 17:10:22",
    "ppv": "2025-10-17 17:02:54",
    "vp2": "2025-10-17 17:12:53",
    "pac": "2025-10-17 08:30:00",
    "overall": "\u2714\ufe0f"
  },
  {
    "station": "kuf",
    "name": "Kufri",
    "state": "Himachal Pradesh",
    "caz": "2025-10-17 17:00:01",
    "ppi": "2025-10-17 17:10:01",
    "sri": "2025-10-17 17:00:01",
    "ppz": "2025-10-17 17:07:03",
    "ppv": "2025-10-17 17:10:01",
    "vp2": "2025-10-17 17:00:01",
    "pac": "2025-10-12 08:30:01",
    "overall": "\u2714\ufe0f"
  },
  {
    "station": "kkl",
    "name": "Karaikal",
    "state": "Puducherry",
    "caz": "2025-10-17 17:13:59",
    "ppi": "2025-10-17 17:13:59",
    "sri": "2025-10-17 17:13:59",
    "ppz": "2025-10-17 17:21:28",
    "ppv": "2025-10-17 17:13:59",
    "vp2": "2025-10-17 17:13:59",
    "pac": "2025-10-17 08:30:00",
    "overall": "\u2714\ufe0f"
  },
  {
    "station": "kol",
    "name": "Kolkata",
    "state": "West Bengal",
    "caz": "2025-10-17 14:12:00",
    "ppi": "2025-10-17 14:12:00",
    "sri": "2025-10-17 14:12:00",
    "ppz": "2025-10-16 10:40:00",
    "ppv": "2025-10-17 14:12:00",
    "vp2": "2025-10-17 14:12:00",
    "pac": "2025-10-11 08:32:00",
    "overall": "\u2714\ufe0f: Stand By Mode"
  },
  {
    "station": "koc",
    "name": "Kochi",
    "state": "Kerala",
    "caz": "2025-10-17 17:00:03",
    "ppi": "2025-10-17 17:00:03",
    "sri": "2025-10-17 17:15:16",
    "ppz": "2025-10-17 17:13:52",
    "ppv": "2025-10-17 17:25:01",
    "vp2": "2025-10-17 17:15:16",
    "pac": "2025-10-17 16:58:39",
    "overall": "\u2714\ufe0f"
  },
  {
    "station": "leh",
    "name": "Leh",
    "state": "Ladakh",
    "caz": "2025-10-03 15:30:01",
    "ppi": "2025-10-03 15:50:01",
    "sri": "2025-10-03 15:40:01",
    "ppz": "Missing",
    "ppv": "2025-10-03 15:50:01",
    "vp2": "2025-10-03 15:30:01",
    "pac": "2025-10-17 17:25:01",
    "overall": "\u274c"
  },
  {
    "station": "ldn",
    "name": "Lansdowne",
    "state": "Uttrakhand",
    "caz": "2025-10-17 16:20:01",
    "ppi": "2025-10-17 16:50:01",
    "sri": "2025-10-17 16:40:01",
    "ppz": "2025-10-17 16:46:53",
    "ppv": "2025-10-17 16:50:01",
    "vp2": "2025-10-17 16:40:01",
    "pac": "2025-10-17 08:30:01",
    "overall": "\u2714\ufe0f"
  },
  {
    "station": "lkn",
    "name": "Lucknow",
    "state": "Uttar Pradesh",
    "caz": "2025-10-17 17:12:11",
    "ppi": "Invalid",
    "sri": "2025-10-17 17:22:12",
    "ppz": "2025-10-17 17:20:15",
    "ppv": "2025-10-17 17:12:11",
    "vp2": "2025-10-17 17:12:11",
    "pac": "2025-10-17 08:30:00",
    "overall": "\u2714\ufe0f"
  },
  {
    "station": "mks",
    "name": "Mukteshwar",
    "state": "Uttrakhand",
    "manual_status": "DWR SHUTDOWN DUE TO FAULTY ENCODER AND AZIMUTH MOTOR Since 2025-09-08",
    "overall": "\u274c"
  },
  {
    "station": "mur",
    "name": "Murari Devi",
    "state": "Himachal Pradesh",
    "manual_status": "Servo link issue Since 2025-09-12",
    "overall": "\u274c"
  },
  {
    "station": "mbr",
    "name": "Mohanbari",
    "state": "Assam",
    "manual_status": "Under Maintenance Since 2025-08-13",
    "overall": "\u274c"
  },
  {
    "station": "mpt",
    "name": "Machilipatnam",
    "state": "Andhra Pradesh",
    "caz": "2025-10-17 17:02:00",
    "ppi": "2025-10-17 17:02:00",
    "sri": "2025-10-17 17:02:00",
    "ppz": "2025-10-17 17:10:00",
    "ppv": "2025-10-17 17:02:00",
    "vp2": "2025-10-17 17:02:00",
    "pac": "2025-10-17 08:32:00",
    "overall": "\u2714\ufe0f"
  },
  {
    "station": "mum",
    "name": "Mumbai",
    "state": "Maharashtra",
    "caz": "2025-10-17 16:34:38",
    "ppi": "2025-10-17 16:34:38",
    "sri": "2025-10-17 16:34:38",
    "ppz": "2025-10-17 16:33:14",
    "ppv": "2025-10-17 16:34:38",
    "vp2": "2025-10-17 16:04:25",
    "pac": "2025-10-17 08:00:56",
    "overall": "\u2714\ufe0f"
  },
  {
    "station": "ngp",
    "name": "Nagpur",
    "state": "Maharashtra",
    "caz": "2025-10-17 17:12:20",
    "ppi": "2025-10-17 17:12:20",
    "sri": "2025-10-17 17:12:20",
    "ppz": "2025-10-17 17:20:23",
    "ppv": "2025-10-17 17:12:20",
    "vp2": "2025-10-17 17:12:20",
    "pac": "2025-10-17 08:30:00",
    "overall": "\u2714\ufe0f"
  },
  {
    "station": "pdp",
    "name": "Paradip",
    "state": "Odhisa",
    "caz": "2025-10-17 17:22:18",
    "ppi": "2025-10-17 17:22:18",
    "sri": "2025-10-17 17:22:18",
    "ppz": "2025-10-17 17:30:24",
    "ppv": "2025-10-17 17:22:18",
    "vp2": "2025-10-17 17:22:18",
    "pac": "2025-10-17 14:30:00",
    "overall": "\u2714\ufe0f"
  },
  {
    "station": "plk",
    "name": "Pallikarni",
    "state": "Tamilnadu",
    "caz": "2025-10-17 17:09:01",
    "ppi": "2025-10-17 17:09:01",
    "sri": "2025-10-17 17:09:01",
    "ppz": "2025-10-17 17:07:03",
    "ppv": "2025-10-17 17:09:01",
    "vp2": "2025-10-17 17:16:10",
    "pac": "2025-10-17 07:55:46",
    "overall": "\u2714\ufe0f"
  },
  {
    "station": "ptn",
    "name": "Patna",
    "state": "Bihar",
    "caz": "2025-10-17 17:12:23",
    "ppi": "2025-10-17 17:12:23",
    "sri": "2025-10-17 17:12:23",
    "ppz": "2025-10-17 17:20:25",
    "ppv": "2025-10-17 17:12:23",
    "vp2": "2025-10-17 17:12:23",
    "pac": "2025-10-17 08:30:00",
    "overall": "\u2714\ufe0f"
  },
  {
    "station": "ptl",
    "name": "Patiala",
    "state": "Punjab",
    "caz": "2025-10-17 17:12:22",
    "ppi": "2025-10-17 17:12:22",
    "sri": "2025-10-17 17:12:22",
    "ppz": "2025-10-17 16:40:26",
    "ppv": "2025-10-17 17:12:22",
    "vp2": "2025-10-17 17:12:22",
    "pac": "2025-10-17 08:30:00",
    "overall": "\u2714\ufe0f"
  },
  {
    "station": "rpr",
    "name": "Raipur",
    "state": "Chattisgarh",
    "caz": "2025-10-17 17:25:01",
    "ppi": "2025-10-17 17:25:01",
    "sri": "2025-10-17 17:25:01",
    "ppz": "2025-10-17 17:25:02",
    "ppv": "2025-10-17 17:25:01",
    "vp2": "2025-10-17 17:25:02",
    "pac": "2025-10-17 17:25:01",
    "overall": "\u2714\ufe0f"
  },
  {
    "station": "shr",
    "name": "Sriharikota",
    "state": "Andhra Pradesh",
    "caz": "2025-10-17 16:07:27",
    "ppi": "2025-10-17 16:07:27",
    "sri": "2025-10-17 16:07:27",
    "ppz": "2025-10-17 17:04:15",
    "ppv": "2025-10-17 16:07:27",
    "vp2": "2025-10-17 16:07:27",
    "pac": "2025-10-16 08:01:02",
    "overall": "\u2714\ufe0f"
  },
  {
    "station": "sur",
    "name": "Surkanda Devi",
    "state": "Uttrakhand",
    "manual_status": "Power Issue Since 2025-05-30",
    "overall": "\u274c"
  },
  {
    "station": "slp",
    "name": "Solapur",
    "state": "Maharashtra",
    "caz": "Missing",
    "ppi": "Missing",
    "sri": "Missing",
    "ppz": "Missing",
    "ppv": "Missing",
    "vp2": "Missing",
    "pac": "Missing",
    "overall": "\u274c"
  },
  {
    "station": "srn",
    "name": "Srinagar",
    "state": "Jammu & Kashmir",
    "caz": "2025-10-17 17:00:00",
    "ppi": "2025-10-17 16:30:00",
    "sri": "2025-10-17 16:20:00",
    "ppz": "2025-10-17 16:30:00",
    "ppv": "2025-10-17 16:20:00",
    "vp2": "2025-10-17 13:00:00",
    "pac": "2025-10-17 08:30:00",
    "overall": "\u2714\ufe0f"
  },
  {
    "station": "tvm",
    "name": "Trivandrum",
    "state": "Kerala",
    "caz": "2025-10-17 17:05:49",
    "ppi": "2025-10-17 17:05:49",
    "sri": "2025-10-17 16:35:08",
    "ppz": "2025-10-17 17:03:11",
    "ppv": "2025-10-17 17:05:49",
    "vp2": "2025-10-17 16:50:27",
    "pac": "2025-10-17 16:19:50",
    "overall": "\u2714\ufe0f"
  },
  {
    "station": "vrv",
    "name": "Veravali",
    "state": "Maharashtra",
    "caz": "2025-10-17 17:06:22",
    "ppi": "2025-10-17 17:06:22",
    "sri": "2025-10-17 17:06:22",
    "ppz": "2025-10-17 17:04:33",
    "ppv": "2025-10-17 17:06:22",
    "vp2": "2025-10-17 17:12:06",
    "pac": "2025-10-17 13:25:22",
    "overall": "\u2714\ufe0f"
  },
  {
    "station": "vsk",
    "name": "Visakhapatnam",
    "state": "Andhra Pradesh",
    "caz": "2025-10-17 16:30:00",
    "ppi": "2025-10-17 16:30:00",
    "sri": "2025-10-17 16:30:00",
    "ppz": "2025-10-17 16:28:00",
    "ppv": "2025-10-17 16:30:00",
    "vp2": "2025-10-17 16:30:00",
    "pac": "2025-10-17 08:30:00",
    "overall": "\u2714\ufe0f"
  }
]