[
  {
    "station": "agt",
    "caz": "2025-09-04 20:42:24",
    "ppi": "2025-09-04 20:42:24",
    "sri": "2025-09-04 20:32:24",
    "ppz": "2025-09-04 20:30:27",
    "ppv": "2025-09-04 20:32:24",
    "vp2": "2025-09-04 20:32:24",
    "pac": "2025-09-04 08:30:00",
    "overall": "\u2714\ufe0f"
  },
  {
    "station": "aya",
    "caz": "2025-09-04 20:10:01",
    "ppi": "2025-09-04 20:20:01",
    "sri": "2025-09-04 20:10:01",
    "ppz": "2025-09-04 20:16:56",
    "ppv": "2025-09-04 20:20:01",
    "vp2": "2025-09-04 20:10:01",
    "pac": "2025-09-04 08:30:02",
    "overall": "\u2714\ufe0f"
  },
  {
    "station": "bnh",
    "caz": "2025-09-04 18:00:02",
    "ppi": "2025-09-04 18:10:02",
    "sri": "2025-09-04 18:10:02",
    "ppz": "2025-09-04 18:06:54",
    "ppv": "2025-09-04 18:10:02",
    "vp2": "2025-09-04 17:00:02",
    "pac": "2025-09-03 08:30:01",
    "overall": "\u274c"
  },
  {
    "station": "bhj",
    "caz": "2025-09-04 19:31:09",
    "ppi": "2025-09-04 20:31:38",
    "sri": "2025-09-04 17:30:21",
    "ppz": "2025-09-04 00:51:54",
    "ppv": "2025-09-04 18:30:46",
    "vp2": "2025-09-04 19:00:59",
    "pac": "2025-09-01 02:47:06",
    "overall": "\u274c"
  },
  {
    "station": "bhp",
    "caz": "2025-09-04 20:42:21",
    "ppi": "2025-09-04 20:42:21",
    "sri": "2025-09-04 20:32:21",
    "ppz": "2025-09-04 20:40:27",
    "ppv": "2025-09-04 20:32:21",
    "vp2": "2025-09-04 20:32:21",
    "pac": "2025-09-04 08:30:00",
    "overall": "\u2714\ufe0f"
  },
  {
    "station": "cpj",
    "caz": "2025-08-17 09:32:48",
    "ppi": "2025-08-17 09:32:48",
    "sri": "2025-08-17 09:32:48",
    "ppz": "2025-08-17 09:31:03",
    "ppv": "2025-08-17 09:32:48",
    "vp2": "2025-08-17 09:32:48",
    "pac": "2025-05-23 21:55:27",
    "overall": "\u274c"
  },
  {
    "station": "cni",
    "caz": "2025-09-04 20:39:00",
    "ppi": "Missing",
    "sri": "2025-09-04 20:09:00",
    "ppz": "2025-09-04 20:31:00",
    "ppv": "2025-09-04 20:09:00",
    "vp2": "Missing",
    "pac": "2025-09-04 08:30:00",
    "overall": "\u274c"
  },
  {
    "station": "dli",
    "caz": "2025-08-05 15:32:17",
    "ppi": "2025-08-05 15:32:17",
    "sri": "2025-08-05 15:32:17",
    "ppz": "2025-08-06 14:30:00",
    "ppv": "2025-08-05 15:32:17",
    "vp2": "2025-08-05 15:32:17",
    "pac": "2025-08-06 08:30:00",
    "overall": "\u274c"
  },
  {
    "station": "dlh",
    "caz": "2025-09-04 20:42:23",
    "ppi": "2025-09-04 20:32:57",
    "sri": "2025-09-04 20:32:24",
    "ppz": "Invalid",
    "ppv": "2025-09-04 20:32:24",
    "vp2": "2025-09-04 20:32:24",
    "pac": "2025-09-04 08:30:00",
    "overall": "\u274c"
  },
  {
    "station": "goa",
    "caz": "2025-09-04 20:42:34",
    "ppi": "2025-09-04 20:36:59",
    "sri": "2025-09-04 20:32:34",
    "ppz": "2025-09-04 20:30:30",
    "ppv": "2025-09-04 20:37:32",
    "vp2": "2025-09-04 20:32:34",
    "pac": "2025-09-04 08:30:00",
    "overall": "\u2714\ufe0f"
  },
  {
    "station": "gop",
    "caz": "Missing",
    "ppi": "Missing",
    "sri": "Missing",
    "ppz": "Missing",
    "ppv": "Missing",
    "vp2": "Missing",
    "pac": "Missing",
    "overall": "\u274c"
  },
  {
    "station": "hyd",
    "caz": "2025-09-04 20:35:37",
    "ppi": "2025-09-04 20:16:38",
    "sri": "2025-09-04 20:16:38",
    "ppz": "2025-09-04 20:33:14",
    "ppv": "2025-09-04 20:16:38",
    "vp2": "2025-09-04 20:16:38",
    "pac": "2025-09-04 08:30:00",
    "overall": "\u2714\ufe0f"
  },
  {
    "station": "jot",
    "caz": "Missing",
    "ppi": "2025-09-04 17:20:01",
    "sri": "Missing",
    "ppz": "2025-09-04 17:26:55",
    "ppv": "Missing",
    "vp2": "2025-09-04 17:10:01",
    "pac": "2025-09-04 08:30:02",
    "overall": "\u274c"
  },
  {
    "station": "jmu",
    "caz": "2025-09-02 14:40:01",
    "ppi": "2025-09-02 14:50:01",
    "sri": "2025-09-02 14:40:01",
    "ppz": "Missing",
    "ppv": "2025-09-02 15:00:01",
    "vp2": "2025-09-02 13:40:01",
    "pac": "2025-09-02 08:30:01",
    "overall": "\u274c"
  },
  {
    "station": "jpr",
    "caz": "Invalid",
    "ppi": "2025-09-04 20:22:53",
    "sri": "2025-09-04 20:22:53",
    "ppz": "2025-09-04 20:30:21",
    "ppv": "2025-09-04 20:22:53",
    "vp2": "2025-09-04 20:22:53",
    "pac": "2025-09-04 08:30:00",
    "overall": "\u274c"
  },
  {
    "station": "kuf",
    "caz": "2025-09-04 20:10:01",
    "ppi": "2025-09-04 20:00:01",
    "sri": "2025-09-04 19:50:01",
    "ppz": "2025-09-04 19:57:03",
    "ppv": "2025-09-04 20:00:01",
    "vp2": "2025-09-04 19:50:01",
    "pac": "2025-09-04 08:30:01",
    "overall": "\u274c"
  },
  {
    "station": "kkl",
    "caz": "2025-09-04 19:41:40",
    "ppi": "2025-09-04 19:41:40",
    "sri": "2025-09-04 19:20:29",
    "ppz": "2025-09-04 20:23:21",
    "ppv": "2025-09-04 19:41:40",
    "vp2": "2025-09-04 19:30:41",
    "pac": "2025-09-04 08:30:00",
    "overall": "\u274c"
  },
  {
    "station": "kol",
    "caz": "2025-09-04 18:22:00",
    "ppi": "2025-09-04 18:22:00",
    "sri": "2025-09-04 18:22:00",
    "ppz": "2025-09-04 18:20:00",
    "ppv": "2025-09-04 18:11:00",
    "vp2": "2025-09-04 18:11:00",
    "pac": "2025-09-04 09:20:00",
    "overall": "\u274c"
  },
  {
    "station": "koc",
    "caz": "2025-04-09 20:27:21",
    "ppi": "2025-04-09 20:27:21",
    "sri": "2025-09-04 20:27:21",
    "ppz": "2025-04-09 20:25:57",
    "ppv": "Missing",
    "vp2": "2025-09-04 20:12:08",
    "pac": "2025-09-04 19:55:32",
    "overall": "\u274c"
  },
  {
    "station": "leh",
    "caz": "2025-09-04 19:10:01",
    "ppi": "2025-09-04 19:50:01",
    "sri": "2025-09-04 19:10:01",
    "ppz": "Missing",
    "ppv": "2025-09-04 19:50:01",
    "vp2": "2025-09-04 19:10:01",
    "pac": "Missing",
    "overall": "\u274c"
  },
  {
    "station": "ldn",
    "caz": "2025-09-04 20:10:01",
    "ppi": "2025-09-04 20:20:01",
    "sri": "2025-09-04 20:10:01",
    "ppz": "2025-09-02 00:46:53",
    "ppv": "2025-09-04 20:20:01",
    "vp2": "2025-09-04 20:10:01",
    "pac": "2025-09-04 08:30:01",
    "overall": "\u274c"
  },
  {
    "station": "lkn",
    "caz": "2025-09-04 20:52:11",
    "ppi": "2025-09-04 20:42:12",
    "sri": "2025-09-04 20:42:12",
    "ppz": "2025-09-04 20:40:15",
    "ppv": "2025-09-04 20:42:12",
    "vp2": "2025-09-04 20:42:12",
    "pac": "2025-09-04 08:30:00",
    "overall": "\u2714\ufe0f"
  },
  {
    "station": "mks",
    "caz": "2025-09-04 20:00:01",
    "ppi": "2025-09-04 20:10:01",
    "sri": "2025-09-04 19:40:01",
    "ppz": "2025-09-04 20:06:52",
    "ppv": "2025-09-04 20:10:01",
    "vp2": "2025-09-04 19:40:01",
    "pac": "2025-09-04 08:30:01",
    "overall": "\u274c"
  },
  {
    "station": "mur",
    "caz": "2025-09-04 20:30:01",
    "ppi": "2025-09-04 20:10:01",
    "sri": "2025-09-04 10:30:01",
    "ppz": "2025-09-04 20:06:58",
    "ppv": "2025-09-04 20:10:01",
    "vp2": "2025-09-04 10:30:01",
    "pac": "2025-09-04 08:30:01",
    "overall": "\u274c"
  },
  {
    "station": "mbr",
    "caz": "Missing",
    "ppi": "Missing",
    "sri": "Missing",
    "ppz": "Missing",
    "ppv": "Missing",
    "vp2": "Missing",
    "pac": "Missing",
    "overall": "\u274c"
  },
  {
    "station": "mpt",
    "caz": "2025-09-04 20:42:00",
    "ppi": "2025-09-04 20:32:00",
    "sri": "2025-09-04 20:32:00",
    "ppz": "2025-09-04 20:30:00",
    "ppv": "2025-09-04 20:32:00",
    "vp2": "2025-09-04 20:32:00",
    "pac": "202-09-04 08:32:00",
    "overall": "\u274c"
  },
  {
    "station": "mum",
    "caz": "2025-09-04 20:31:11",
    "ppi": "2025-09-04 20:31:11",
    "sri": "2025-09-04 20:31:11",
    "ppz": "2025-09-04 20:29:50",
    "ppv": "2025-09-04 20:31:11",
    "vp2": "2025-09-04 20:01:01",
    "pac": "2025-09-04 08:07:16",
    "overall": "\u2714\ufe0f"
  },
  {
    "station": "ngp",
    "caz": "2025-09-04 20:42:20",
    "ppi": "2025-09-04 20:32:20",
    "sri": "2025-09-04 20:32:20",
    "ppz": "2025-09-04 20:40:23",
    "ppv": "2025-09-04 20:32:20",
    "vp2": "2025-09-04 20:32:20",
    "pac": "2025-09-04 08:30:00",
    "overall": "\u2714\ufe0f"
  },
  {
    "station": "pdp",
    "caz": "2025-09-04 20:42:18",
    "ppi": "2025-09-04 20:32:22",
    "sri": "2025-09-04 20:32:22",
    "ppz": "2025-09-04 20:40:24",
    "ppv": "2025-09-04 20:32:22",
    "vp2": "2025-09-04 20:32:22",
    "pac": "2025-09-04 20:30:00",
    "overall": "\u2714\ufe0f"
  },
  {
    "station": "plk",
    "caz": "2025-09-04 20:39:18",
    "ppi": "2025-09-04 20:30:13",
    "sri": "2025-09-04 20:30:13",
    "ppz": "2025-09-04 20:28:16",
    "ppv": "2025-09-04 20:30:13",
    "vp2": "2025-09-04 20:37:21",
    "pac": "2025-09-04 07:53:51",
    "overall": "\u2714\ufe0f"
  },
  {
    "station": "ptn",
    "caz": "2025-09-04 20:42:22",
    "ppi": "2025-09-04 20:32:23",
    "sri": "2025-09-04 20:32:23",
    "ppz": "2025-09-04 20:30:25",
    "ppv": "2025-09-04 20:32:23",
    "vp2": "2025-09-04 20:32:23",
    "pac": "2025-09-04 08:30:00",
    "overall": "\u2714\ufe0f"
  },
  {
    "station": "ptl",
    "caz": "2025-09-04 20:42:24",
    "ppi": "2025-09-04 20:32:27",
    "sri": "2025-09-04 20:32:27",
    "ppz": "2025-09-04 20:30:25",
    "ppv": "2025-09-04 20:32:27",
    "vp2": "2025-09-04 20:32:27",
    "pac": "2025-09-04 08:30:00",
    "overall": "\u2714\ufe0f"
  },
  {
    "station": "rpr",
    "caz": "Missing",
    "ppi": "Missing",
    "sri": "Missing",
    "ppz": "Missing",
    "ppv": "Missing",
    "vp2": "Missing",
    "pac": "Missing",
    "overall": "\u274c"
  },
  {
    "station": "shr",
    "caz": "2025-09-04 20:00:41",
    "ppi": "2025-09-04 20:00:41",
    "sri": "2025-09-04 20:00:41",
    "ppz": "2025-09-04 19:58:15",
    "ppv": "2025-09-04 20:00:41",
    "vp2": "2025-09-04 19:01:28",
    "pac": "2025-09-04 08:07:32",
    "overall": "\u274c"
  },
  {
    "station": "sur",
    "caz": "2025-08-21 14:30:02",
    "ppi": "2025-08-21 14:40:02",
    "sri": "2025-08-21 14:30:02",
    "ppz": "2025-08-21 14:36:55",
    "ppv": "2025-08-21 14:40:02",
    "vp2": "2025-08-21 14:30:02",
    "pac": "2025-05-30 12:00:01",
    "overall": "\u274c"
  },
  {
    "station": "slp",
    "caz": "Missing",
    "ppi": "Missing",
    "sri": "Missing",
    "ppz": "Missing",
    "ppv": "Missing",
    "vp2": "Missing",
    "pac": "Missing",
    "overall": "\u274c"
  },
  {
    "station": "srn",
    "caz": "2025-09-04 20:30:00",
    "ppi": "2025-09-04 19:30:00",
    "sri": "2025-09-04 20:20:00",
    "ppz": "2025-09-04 19:30:00",
    "ppv": "2025-09-04 19:30:00",
    "vp2": "2025-09-04 20:20:00",
    "pac": "2025-09-04 08:30:00",
    "overall": "\u274c"
  },
  {
    "station": "tvm",
    "caz": "2025-09-04 20:20:39",
    "ppi": "2025-09-04 20:20:39",
    "sri": "2025-09-04 20:20:39",
    "ppz": "2025-09-04 20:18:01",
    "ppv": "2025-09-04 20:20:39",
    "vp2": "2025-09-04 20:20:39",
    "pac": "2025-09-04 20:20:39",
    "overall": "\u2714\ufe0f"
  },
  {
    "station": "vrv",
    "caz": "2025-09-04 20:34:38",
    "ppi": "2025-09-04 20:27:05",
    "sri": "2025-09-04 20:27:05",
    "ppz": "2025-09-04 20:32:49",
    "ppv": "2025-09-04 20:27:05",
    "vp2": "2025-09-04 20:32:49",
    "pac": "2025-09-04 13:24:49",
    "overall": "\u2714\ufe0f"
  },
  {
    "station": "vsk",
    "caz": "2025-09-04 20:30:00",
    "ppi": "2025-09-04 20:30:00",
    "sri": "2025-09-04 20:30:00",
    "ppz": "2025-09-04 20:28:00",
    "ppv": "2025-09-04 20:30:00",
    "vp2": "2025-09-04 20:30:00",
    "pac": "2025-09-04 08:30:00",
    "overall": "\u2714\ufe0f"
  }
]